swarmauri_workflow_statedriven/__init__.py
swarmauri_workflow_statedriven/base.py
swarmauri_workflow_statedriven/conditions/__init__.py
swarmauri_workflow_statedriven/conditions/base.py
swarmauri_workflow_statedriven/conditions/composite_condition.py
swarmauri_workflow_statedriven/conditions/function_condition.py
swarmauri_workflow_statedriven/conditions/membership_condition.py
swarmauri_workflow_statedriven/conditions/regex_condition.py
swarmauri_workflow_statedriven/conditions/state_condition.py
swarmauri_workflow_statedriven/conditions/string_condition.py
swarmauri_workflow_statedriven/conditions/time_condition.py
swarmauri_workflow_statedriven/exceptions.py
swarmauri_workflow_statedriven/graph.py
swarmauri_workflow_statedriven/input_modes/__init__.py
swarmauri_workflow_statedriven/input_modes/aggregate.py
swarmauri_workflow_statedriven/input_modes/base.py
swarmauri_workflow_statedriven/input_modes/first.py
swarmauri_workflow_statedriven/input_modes/identity.py
swarmauri_workflow_statedriven/input_modes/last.py
swarmauri_workflow_statedriven/input_modes/split.py
swarmauri_workflow_statedriven/join_strategies/__init__.py
swarmauri_workflow_statedriven/join_strategies/aggregator.py
swarmauri_workflow_statedriven/join_strategies/all_join.py
swarmauri_workflow_statedriven/join_strategies/base.py
swarmauri_workflow_statedriven/join_strategies/conditional_join.py
swarmauri_workflow_statedriven/join_strategies/first_join.py
swarmauri_workflow_statedriven/join_strategies/n_of_m_join.py
swarmauri_workflow_statedriven/join_strategies/per_arrival_join.py
swarmauri_workflow_statedriven/merge_strategies/__init__.py
swarmauri_workflow_statedriven/merge_strategies/base.py
swarmauri_workflow_statedriven/merge_strategies/concat_merge.py
swarmauri_workflow_statedriven/merge_strategies/custom_merge.py
swarmauri_workflow_statedriven/merge_strategies/dict_merge.py
swarmauri_workflow_statedriven/merge_strategies/flatten_merge.py
swarmauri_workflow_statedriven-0.1.1.dist-info/LICENSE
swarmauri_workflow_statedriven-0.1.1.dist-info/METADATA
swarmauri_workflow_statedriven-0.1.1.dist-info/WHEEL
swarmauri_workflow_statedriven-0.1.1.dist-info/RECORD
